{
    "last_updated": "2025-01-05T22:11:09.567323",
    "prices": [
        {
            "name": "Bitcoin",
            "symbol": "BTC",
            "price": "98,967.72",
            "24-hour change": "+0.83%"
        },
        {
            "name": "Ethereum",
            "symbol": "ETH",
            "price": "3,666.71",
            "24-hour change": "+0.89%"
        },
        {
            "name": "XRP",
            "symbol": "XRP",
            "price": "2.40",
            "24-hour change": "+0.56%"
        },
        {
            "name": "Tether",
            "symbol": "USDT",
            "price": "0.9998",
            "24-hour change": "+0.00%"
        },
        {
            "name": "Solana",
            "symbol": "SOL",
            "price": "216.06",
            "24-hour change": "-0.28%"
        },
        {
            "name": "BNB",
            "symbol": "BNB",
            "price": "714.01",
            "24-hour change": "+0.31%"
        },
        {
            "name": "Dogecoin",
            "symbol": "DOGE",
            "price": "0.3858",
            "24-hour change": "-0.66%"
        },
        {
            "name": "USD Coin",
            "symbol": "USDC",
            "price": "1",
            "24-hour change": "+0.02%"
        },
        {
            "name": "Cardano",
            "symbol": "ADA",
            "price": "1.09",
            "24-hour change": "+2.94%"
        },
        {
            "name": "TRON",
            "symbol": "TRX",
            "price": "0.2632",
            "24-hour change": "-1.00%"
        },
        {
            "name": "Avalanche",
            "symbol": "AVAX",
            "price": "43.02",
            "24-hour change": "+2.46%"
        },
        {
            "name": "Wrapped Bitcoin",
            "symbol": "WBTC",
            "price": "98,660.36",
            "24-hour change": "+0.73%"
        },
        {
            "name": "Sui",
            "symbol": "SUI",
            "price": "5.23",
            "24-hour change": "+0.15%"
        },
        {
            "name": "Chainlink",
            "symbol": "LINK",
            "price": "23.75",
            "24-hour change": "+1.87%"
        },
        {
            "name": "Toncoin",
            "symbol": "TON",
            "price": "5.74",
            "24-hour change": "+0.86%"
        },
        {
            "name": "Shiba Inu",
            "symbol": "SHIB",
            "price": "0.00002414",
            "24-hour change": "+0.30%"
        },
        {
            "name": "Stellar",
            "symbol": "XLM",
            "price": "0.4473",
            "24-hour change": "+0.45%"
        },
        {
            "name": "Polkadot",
            "symbol": "DOT",
            "price": "7.76",
            "24-hour change": "+1.95%"
        },
        {
            "name": "Hedera",
            "symbol": "HBAR",
            "price": "0.306",
            "24-hour change": "-0.22%"
        },
        {
            "name": "Bitcoin Cash",
            "symbol": "BCH",
            "price": "474.17",
            "24-hour change": "+0.17%"
        },
        {
            "name": "Uniswap",
            "symbol": "UNI",
            "price": "15.41",
            "24-hour change": "+2.14%"
        },
        {
            "name": "Pepe",
            "symbol": "PEPE",
            "price": "0.00002088",
            "24-hour change": "-1.57%"
        },
        {
            "name": "Litecoin",
            "symbol": "LTC",
            "price": "115.78",
            "24-hour change": "+4.18%"
        },
        {
            "name": "UNUS SED LEO",
            "symbol": "LEO",
            "price": "9.10",
            "24-hour change": "+0.28%"
        },
        {
            "name": "Bitget Token",
            "symbol": "BGB",
            "price": "6.00",
            "24-hour change": "-0.41%"
        },
        {
            "name": "NEAR Protocol",
            "symbol": "NEAR",
            "price": "5.95",
            "24-hour change": "+3.16%"
        },
        {
            "name": "Internet Computer",
            "symbol": "ICP",
            "price": "12.18",
            "24-hour change": "+0.86%"
        },
        {
            "name": "Aptos",
            "symbol": "APT",
            "price": "10.05",
            "24-hour change": "+1.78%"
        },
        {
            "name": "Dai",
            "symbol": "DAI",
            "price": "0.9992",
            "24-hour change": "-0.07%"
        },
        {
            "name": "Aave",
            "symbol": "AAVE",
            "price": "343.49",
            "24-hour change": "-1.02%"
        },
        {
            "name": "Mantle",
            "symbol": "MNT",
            "price": "1.40",
            "24-hour change": "+1.94%"
        },
        {
            "name": "Polygon Ecosystem Token",
            "symbol": "POL",
            "price": "0.5222",
            "24-hour change": "+0.20%"
        },
        {
            "name": "Cronos",
            "symbol": "CRO",
            "price": "0.1595",
            "24-hour change": "-0.66%"
        },
        {
            "name": "Render Token",
            "symbol": "RENDER",
            "price": "8.33",
            "24-hour change": "+3.76%"
        },
        {
            "name": "Ethereum Classic",
            "symbol": "ETC",
            "price": "28.44",
            "24-hour change": "+1.11%"
        },
        {
            "name": "bittensor",
            "symbol": "TAO",
            "price": "566.76",
            "24-hour change": "+1.44%"
        },
        {
            "name": "VeChain",
            "symbol": "VET",
            "price": "0.05149",
            "24-hour change": "+2.09%"
        },
        {
            "name": "Virtual Protocol",
            "symbol": "VIRTUAL",
            "price": "4.10",
            "24-hour change": "-6.31%"
        },
        {
            "name": "Arbitrum",
            "symbol": "ARB",
            "price": "0.9365",
            "24-hour change": "+6.38%"
        },
        {
            "name": "Ethena",
            "symbol": "ENA",
            "price": "1.26",
            "24-hour change": "+4.35%"
        },
        {
            "name": "Artificial Superintelligence Alliance",
            "symbol": "FET",
            "price": "1.60",
            "24-hour change": "+8.10%"
        },
        {
            "name": "Filecoin",
            "symbol": "FIL",
            "price": "6.23",
            "24-hour change": "+11.27%"
        },
        {
            "name": "MANTRA",
            "symbol": "OM",
            "price": "3.93",
            "24-hour change": "-0.51%"
        },
        {
            "name": "WhiteBIT Token",
            "symbol": "WBT",
            "price": "25.89",
            "24-hour change": "+3.53%"
        },
        {
            "name": "Monero",
            "symbol": "XMR",
            "price": "199.56",
            "24-hour change": "+3.43%"
        },
        {
            "name": "Tokenize Xchange",
            "symbol": "TKX",
            "price": "43.72",
            "24-hour change": "-5.09%"
        },
        {
            "name": "Algorand",
            "symbol": "ALGO",
            "price": "0.409",
            "24-hour change": "+0.97%"
        },
        {
            "name": "Kaspa",
            "symbol": "KAS",
            "price": "0.1234",
            "24-hour change": "-1.86%"
        },
        {
            "name": "OKB",
            "symbol": "OKB",
            "price": "50.85",
            "24-hour change": "-0.00%"
        },
        {
            "name": "Cosmos",
            "symbol": "ATOM",
            "price": "7.39",
            "24-hour change": "+1.75%"
        }
    ]
}